planetwatch/__init__.py
planetwatch/core.py
planetwatch/dashboard.py
planetwatch-0.1.9.dist-info/entry_points.txt
planetwatch-0.1.9.dist-info/LICENSE
planetwatch-0.1.9.dist-info/WHEEL
planetwatch-0.1.9.dist-info/METADATA
planetwatch-0.1.9.dist-info/RECORD
