Metadata-Version: 2.1
Name: planetwatch
Version: 0.1.9
Summary: Code to make it easy to calculate earnings, etc for planetwatch
License: GNU General Public License v3.0
Author: errantp
Requires-Python: >=3.7,<4.0
Classifier: License :: Other/Proprietary License
Classifier: Programming Language :: Python :: 3
Classifier: Programming Language :: Python :: 3.10
Classifier: Programming Language :: Python :: 3.7
Classifier: Programming Language :: Python :: 3.8
Classifier: Programming Language :: Python :: 3.9
Requires-Dist: attr
Requires-Dist: click
Requires-Dist: millify (>=0.1.1,<0.2.0)
Requires-Dist: pandas
Requires-Dist: py-algorand-sdk (==1.9.0b2)
Requires-Dist: pycoingecko (>=2.2.0,<3.0.0)
Requires-Dist: streamlit (>=0.88.0)
